django_scatter_auth-0.2.0.dist-info/DESCRIPTION.rst
django_scatter_auth-0.2.0.dist-info/METADATA
django_scatter_auth-0.2.0.dist-info/RECORD
django_scatter_auth-0.2.0.dist-info/WHEEL
django_scatter_auth-0.2.0.dist-info/metadata.json
django_scatter_auth-0.2.0.dist-info/top_level.txt
scatterauth/__init__.py
scatterauth/admin.py
scatterauth/apps.py
scatterauth/backend.py
scatterauth/forms.py
scatterauth/models.py
scatterauth/settings.py
scatterauth/tests.py
scatterauth/urls.py
scatterauth/utils.py
scatterauth/views.py
scatterauth/static/scatterauth/css/scatterauth.css
scatterauth/static/scatterauth/js/scatterauth.js
scatterauth/templates/scatterauth/base.html
scatterauth/templates/scatterauth/signup.html
