Metadata-Version: 2.0
Name: django-scatter-auth
Version: 0.2.0
Summary: django-scatter-auth is a pluggable Django app that enables login/signup via Scatter (EOS). The user authenticates himself by digitally signing the session key with their wallet's private key.
Home-page: https://github.com/Bearle/django-scatter-auth
Author: Bearle
Author-email: tech@bearle.ru
License: MIT
Keywords: django-scatter-auth
Platform: UNKNOWN
Classifier: Development Status :: 3 - Alpha
Classifier: Framework :: Django :: 1.11
Classifier: Framework :: Django :: 2.0
Classifier: Framework :: Django :: 2.1
Classifier: Intended Audience :: Developers
Classifier: License :: OSI Approved :: BSD License
Classifier: Natural Language :: English
Classifier: Programming Language :: Python :: 3
Classifier: Programming Language :: Python :: 3.4
Classifier: Programming Language :: Python :: 3.5
Classifier: Programming Language :: Python :: 3.6
Requires-Dist: fastecdsa (==1.6.4)
Requires-Dist: base58 (==1.0.0)
